archmage/CHM.py
archmage/CHMParser.py
archmage/__init__.py
archmage/arch.conf
archmage/chmtotext.py
archmage/cli.py
archmage/htmldoc.py
archmage/templates/arch_contents.html
archmage/templates/arch_css.css
archmage/templates/arch_frameset.html
archmage/templates/arch_header.html
archmage/templates/index.html
archmage/templates/icons/0.gif
archmage/templates/icons/1.gif
archmage/templates/icons/10.gif
archmage/templates/icons/11.gif
archmage/templates/icons/12.gif
archmage/templates/icons/13.gif
archmage/templates/icons/14.gif
archmage/templates/icons/15.gif
archmage/templates/icons/16.gif
archmage/templates/icons/17.gif
archmage/templates/icons/18.gif
archmage/templates/icons/19.gif
archmage/templates/icons/2.gif
archmage/templates/icons/20.gif
archmage/templates/icons/21.gif
archmage/templates/icons/22.gif
archmage/templates/icons/23.gif
archmage/templates/icons/24.gif
archmage/templates/icons/25.gif
archmage/templates/icons/26.gif
archmage/templates/icons/27.gif
archmage/templates/icons/3.gif
archmage/templates/icons/35.gif
archmage/templates/icons/37.gif
archmage/templates/icons/39.gif
archmage/templates/icons/4.gif
archmage/templates/icons/5.gif
archmage/templates/icons/6.gif
archmage/templates/icons/7.gif
archmage/templates/icons/8.gif
archmage/templates/icons/9.gif
archmage/templates/icons/90.gif
archmage/templates/icons/91.gif
archmage/templates/icons/92.gif
archmage/templates/icons/93.gif
archmage/templates/icons/94.gif
archmage/templates/icons/95.gif
archmage/templates/icons/96.gif
archmage/templates/icons/97.gif
archmage/templates/icons/98.gif
archmage/templates/icons/99.gif
archmage/templates/icons/next.gif
archmage/templates/icons/prev.gif
archmage-0.4.2.1.dist-info/AUTHORS
archmage-0.4.2.1.dist-info/COPYING
archmage-0.4.2.1.dist-info/METADATA
archmage-0.4.2.1.dist-info/WHEEL
archmage-0.4.2.1.dist-info/entry_points.txt
archmage-0.4.2.1.dist-info/top_level.txt
archmage-0.4.2.1.dist-info/RECORD
