Metadata-Version: 2.1
Name: archmage
Version: 0.4.2.1
Summary: CHM decompressor
Home-page: https://github.com/dottedmag/archmage
Maintainer: Mikhail Gusarov
Maintainer-email: dottedmag@dottedmag.net
License: GPLv2+
Keywords: chm,HTML Help,Compiled HTML,Compressed HTML
Platform: UNKNOWN
Classifier: Development Status :: 5 - Production/Stable
Classifier: Environment :: Console
Classifier: Environment :: Web Environment
Classifier: Intended Audience :: End Users/Desktop
Classifier: License :: OSI Approved :: GNU General Public License v2 or later (GPLv2+)
Classifier: Topic :: Text Processing :: Filters
Requires-Dist: pychm
Requires-Dist: beautifulsoup4
Requires-Dist: sgmllib3k
